vlidt/__init__.py
vlidt/abc.py
vlidt/base.py
vlidt/fast.py
vlidt/lazy.py
vlidt/lump.py
vlidt/utils.py
vlidt/validation.py
vlidt-0.2.2.dist-info/METADATA
vlidt-0.2.2.dist-info/WHEEL
vlidt-0.2.2.dist-info/RECORD
