Metadata-Version: 2.1
Name: vlidt
Version: 0.2.2
Summary: dataclass & validation simple as well as hell.
License: MIT
Author: misano
Author-email: me@MirSobhan.ir
Requires-Python: >=3.8,<4.0
Classifier: License :: OSI Approved :: MIT License
Classifier: Programming Language :: Python :: 3
Classifier: Programming Language :: Python :: 3.8
Classifier: Programming Language :: Python :: 3.9
Classifier: Programming Language :: Python :: 3.10
Classifier: Programming Language :: Python :: 3.11
Classifier: Programming Language :: Python :: 3.12
Requires-Dist: typing-validation (>=1.2.11.post4,<2.0.0)
